pubsublib/__init__.py
pubsublib/aws/__init__.py
pubsublib/aws/exceptions.py
pubsublib/aws/main.py
pubsublib/aws/utils/helper.py
pubsublib/common/cache_adapter.py
pubsublib/common/codec.py
pubsublib-0.1.18.dist-info/METADATA
pubsublib-0.1.18.dist-info/WHEEL
pubsublib-0.1.18.dist-info/licenses/LICENSE
pubsublib-0.1.18.dist-info/RECORD
