Metadata-Version: 2.4
Name: pubsublib
Version: 0.1.18
Summary: The Python Adaptation of the PubSubLib for Orange Health
Project-URL: Homepage, https://github.com/Orange-Health/pubsublib-python
Project-URL: Issues, https://github.com/Orange-Health/pubsublib-python/issues
Project-URL: Repository, https://github.com/Orange-Health/pubsublib-python
Author-email: Anant Chauhan <anant.chauhan@orangehealth.in>, Rajendra Talekar <talekar.r@gmail.com>
License-File: LICENSE
Classifier: License :: OSI Approved :: MIT License
Classifier: Operating System :: OS Independent
Classifier: Programming Language :: Python :: 3
Requires-Python: >=3.8
